amoredb/__init__.py
amoredb/brotli.py
amoredb/bson.py
amoredb/core.py
amoredb/gzip.py
amoredb/json.py
amoredb/lz4.py
amoredb/lzma.py
amoredb/snappy.py
amoredb/str.py
amoredb/struct.py
amoredb/fileio/__init__.py
amoredb/fileio/amore_aiofiles.py
amoredb-0.0.3.dist-info/LICENSE
amoredb-0.0.3.dist-info/METADATA
amoredb-0.0.3.dist-info/WHEEL
amoredb-0.0.3.dist-info/top_level.txt
amoredb-0.0.3.dist-info/RECORD
