Metadata-Version: 2.1
Name: amoredb
Version: 0.0.3
Summary: Simple append-only database with rich record formats and compression
Home-page: https://github.com/amateur80lvl/amoredb
Author: amateur80lvl
Author-email: amateur80lvl@gmail.com
Keywords: database
Classifier: Development Status :: 3 - Alpha
Classifier: Intended Audience :: Developers
Classifier: Environment :: Other Environment
Classifier: Programming Language :: Python
Classifier: Operating System :: OS Independent
Classifier: License :: OSI Approved :: GNU Lesser General Public License v3 (LGPLv3)
Classifier: Topic :: Database :: Database Engines/Servers
Classifier: Topic :: Software Development :: Libraries :: Python Modules
License-File: LICENSE
